fastapi_fast_template/__init__.py
fastapi_fast_template/actions/__init__.py
fastapi_fast_template/actions/base.py
fastapi_fast_template/actions/doc.py
fastapi_fast_template/actions/extension.py
fastapi_fast_template/actions/main.py
fastapi_fast_template/cli.py
fastapi_fast_template/content.py
fastapi_fast_template/contents/__init__.py
fastapi_fast_template/contents/configs/config.py
fastapi_fast_template/contents/configs/single_config.py
fastapi_fast_template/contents/envs/.env.sample
fastapi_fast_template/contents/git/.gitignore
fastapi_fast_template/contents/git/.pre-commit-config.yaml
fastapi_fast_template/contents/main/app.py
fastapi_fast_template/contents/main/main.py
fastapi_fast_template/contents/main/stream.py
fastapi_fast_template/contents/odm/beanie.py
fastapi_fast_template/contents/orm/__init__.py
fastapi_fast_template/contents/orm/sqlalchemy.py
fastapi_fast_template/contents/orm/sqlmodel.py
fastapi_fast_template/contents/orm/tortoise.py
fastapi_fast_template/contents/repositories/beanie/base.py
fastapi_fast_template/contents/repositories/sqlalchemy/base.py
fastapi_fast_template/contents/repositories/sqlmodel/base.py
fastapi_fast_template/contents/repositories/tortoise/base.py
fastapi_fast_template/contents/routers/base.py
fastapi_fast_template/contents/ruff.toml
fastapi_fast_template/contents/tasks/__init__.py
fastapi_fast_template/contents/tests/conftest.py
fastapi_fast_template/contents/utils/authx.py
fastapi_fast_template/contents/utils/caching/redis_cache.py
fastapi_fast_template/contents/utils/lifespan.py
fastapi_fast_template/contents/utils/stream_lifespan.py
fastapi_fast_template/utils/__init__.py
fastapi_fast_template/utils/enums.py
fastapi_fast_template/utils/helpers.py
fastapi_fast_template-0.0.7.dist-info/LICENCE
fastapi_fast_template-0.0.7.dist-info/METADATA
fastapi_fast_template-0.0.7.dist-info/WHEEL
fastapi_fast_template-0.0.7.dist-info/entry_points.txt
fastapi_fast_template-0.0.7.dist-info/RECORD
