Metadata-Version: 2.1
Name: fastapi-fast-template
Version: 0.0.7
Summary: This library helps you not get involved in the complexities of FastAPI and its libraries and focus all your attention on the application.
Home-page: https://github.com/heysaeid/fastapi-fast-template
License: MIT
Keywords: fastapi,fastapi template,fastapi fast template,fastapi boilerplate
Author: Saeid Noormohammadi
Author-email: heysaeid92@gmail.com
Requires-Python: >=3.7,<4.0
Classifier: Environment :: Web Environment
Classifier: Framework :: AsyncIO
Classifier: Framework :: FastAPI
Classifier: Framework :: Pydantic
Classifier: Intended Audience :: Developers
Classifier: Intended Audience :: Information Technology
Classifier: Intended Audience :: System Administrators
Classifier: License :: OSI Approved :: MIT License
Classifier: Operating System :: OS Independent
Classifier: Programming Language :: Python
Classifier: Programming Language :: Python :: 3
Classifier: Programming Language :: Python :: 3.7
Classifier: Programming Language :: Python :: 3.8
Classifier: Programming Language :: Python :: 3.9
Classifier: Programming Language :: Python :: 3.10
Classifier: Programming Language :: Python :: 3.11
Classifier: Programming Language :: Python :: 3.12
Classifier: Programming Language :: Python :: 3.13
Classifier: Programming Language :: Python :: 3 :: Only
Classifier: Topic :: Internet
Classifier: Topic :: Internet :: WWW/HTTP
Classifier: Topic :: Internet :: WWW/HTTP :: HTTP Servers
Classifier: Topic :: Software Development
Classifier: Topic :: Software Development :: Libraries
Classifier: Topic :: Software Development :: Libraries :: Application Frameworks
Classifier: Topic :: Software Development :: Libraries :: Python Modules
Classifier: Typing :: Typed
Requires-Dist: StrEnum
Requires-Dist: asyncpg
Requires-Dist: fastapi
Requires-Dist: pre-commit
Requires-Dist: pydantic
Requires-Dist: pydantic-settings
Requires-Dist: python-dotenv
Requires-Dist: ruff
Requires-Dist: termcolor
Requires-Dist: uvicorn
Project-URL: Documentation, https://github.com/heysaeid/fastapi-fast-template
Project-URL: Repository, https://github.com/heysaeid/fastapi-fast-template
